zenbitlib/__init__.py
zenbitlib/zenproject.py
zenbitlib/zenutils.py
zenbitlib-0.0.5.dist-info/LICENSE
zenbitlib-0.0.5.dist-info/METADATA
zenbitlib-0.0.5.dist-info/WHEEL
zenbitlib-0.0.5.dist-info/top_level.txt
zenbitlib-0.0.5.dist-info/RECORD
