Metadata-Version: 2.1
Name: zenbitlib
Version: 0.0.5
Summary: A package for quick qml learning
Author-email: zenzenwang <zenwang@outlook.com>
Project-URL: Homepage, https://github.com/zenzen891/zenlib/
Project-URL: Bug Tracker, https://github.com/zenzen891/zenlib/
Classifier: Programming Language :: Python :: 3
Classifier: License :: OSI Approved :: MIT License
Classifier: Operating System :: OS Independent
Requires-Python: >=3.7
License-File: LICENSE
